draftmk_mkdocs_role_filter_plugin-0.2.0.dist-info/licenses/LICENSE
role_filter_plugin/__init__.py
role_filter_plugin/plugin.py
draftmk_mkdocs_role_filter_plugin-0.2.0.dist-info/METADATA
draftmk_mkdocs_role_filter_plugin-0.2.0.dist-info/WHEEL
draftmk_mkdocs_role_filter_plugin-0.2.0.dist-info/entry_points.txt
draftmk_mkdocs_role_filter_plugin-0.2.0.dist-info/top_level.txt
draftmk_mkdocs_role_filter_plugin-0.2.0.dist-info/RECORD
