Metadata-Version: 2.4
Name: draftmk-mkdocs-role-filter-plugin
Version: 0.2.0
Summary: MkDocs plugin for Draftmk to filter documentation by user roles
Author-email: Jonatan Mata <jonmatum@gmail.com>
License-Expression: MIT
Project-URL: Homepage, https://github.com/jonmatum/draftmk-mkdocs-role-filter-plugin
Project-URL: Issues, https://github.com/jonmatum/draftmk-mkdocs-role-filter-plugin/issues
Classifier: Programming Language :: Python :: 3
Classifier: Framework :: MkDocs
Classifier: Operating System :: OS Independent
Requires-Python: >=3.8
License-File: LICENSE
Dynamic: license-file
